CHANGES.txt
LICENSE.txt
MANIFEST.in
README.txt
setup.py
bin/i3minator
docs/info.txt
i3minator/__init__.py
i3minator.egg-info/PKG-INFO
i3minator.egg-info/SOURCES.txt
i3minator.egg-info/dependency_links.txt
i3minator.egg-info/requires.txt
i3minator.egg-info/top_level.txt