Metadata-Version: 1.0
Name: i3minator
Version: 0.0.2
Summary: i3 project manager similar to tmuxinator
Home-page: https://github.com/carlesso/i3minator
Author: Enrico Carlesso
Author-email: enricocarlesso@gmail.com
License: LICENSE.txt
Platform: UNKNOWN
